simplecalc_brykim/calculator.py
simplecalc_brykim-0.1.1.dist-info/METADATA
simplecalc_brykim-0.1.1.dist-info/WHEEL
simplecalc_brykim-0.1.1.dist-info/top_level.txt
simplecalc_brykim-0.1.1.dist-info/RECORD
