Metadata-Version: 2.1
Name: simplecalc-brykim
Version: 0.1.1
Summary: A simple Python calculator
Home-page: UNKNOWN
Author: Your Name
Author-email: youremail@example.com
License: UNKNOWN
Platform: UNKNOWN
Requires-Dist: numpy
